odoo8_addon_l10n_br_account_payment_boleto-8.0.1.0.0.99.dev24-py2.7-nspkg.pth
odoo8_addon_l10n_br_account_payment_boleto-8.0.1.0.0.99.dev24.dist-info/METADATA
odoo8_addon_l10n_br_account_payment_boleto-8.0.1.0.0.99.dev24.dist-info/RECORD
odoo8_addon_l10n_br_account_payment_boleto-8.0.1.0.0.99.dev24.dist-info/WHEEL
odoo8_addon_l10n_br_account_payment_boleto-8.0.1.0.0.99.dev24.dist-info/namespace_packages.txt
odoo8_addon_l10n_br_account_payment_boleto-8.0.1.0.0.99.dev24.dist-info/top_level.txt
odoo_addons/l10n_br_account_payment_boleto/README.rst
odoo_addons/l10n_br_account_payment_boleto/__init__.py
odoo_addons/l10n_br_account_payment_boleto/__openerp__.py
odoo_addons/l10n_br_account_payment_boleto/data/boleto_data.xml
odoo_addons/l10n_br_account_payment_boleto/demo/account_invoice_demo.xml
odoo_addons/l10n_br_account_payment_boleto/demo/payment_demo.xml
odoo_addons/l10n_br_account_payment_boleto/models/__init__.py
odoo_addons/l10n_br_account_payment_boleto/models/account.py
odoo_addons/l10n_br_account_payment_boleto/models/account_invoice.py
odoo_addons/l10n_br_account_payment_boleto/models/account_move_line.py
odoo_addons/l10n_br_account_payment_boleto/models/payment_mode.py
odoo_addons/l10n_br_account_payment_boleto/models/res_company.py
odoo_addons/l10n_br_account_payment_boleto/static/description/icon.png
odoo_addons/l10n_br_account_payment_boleto/views/account_move_line.xml
odoo_addons/l10n_br_account_payment_boleto/views/account_view.xml
odoo_addons/l10n_br_account_payment_boleto/views/payment_mode.xml
odoo_addons/l10n_br_account_payment_boleto/views/res_company.xml
