Metadata-Version: 2.1
Name: odoo8-addon-l10n-br-account-payment-boleto
Version: 8.0.1.0.0.99.dev24
Summary: Adds payment mode boleto on move lines
Home-page: http://www.kmee.com.br
Author: KMEE, Odoo Community Association (OCA)
Author-email: support@odoo-community.org
License: AGPL-3
Platform: UNKNOWN
Classifier: Programming Language :: Python
Classifier: Framework :: Odoo
Classifier: License :: OSI Approved :: GNU Affero General Public License v3
Requires-Python: ~=2.7
Requires-Dist: odoo8-addon-account-due-list
Requires-Dist: odoo8-addon-base-transaction-id
Requires-Dist: odoo8-addon-l10n-br-account-payment-mode
Requires-Dist: odoo (<9.0a,>=8.0a)
